dbcpy/__init__.py
dbcpy/bytes_util.py
dbcpy/dbc_file.py
dbcpy/dbc_header.py
dbcpy/loc.py
dbcpy/records/__init__.py
dbcpy/records/char_title_record.py
dbcpy/records/creature_display_info.py
dbcpy/records/creature_model_data.py
dbcpy/records/creature_sound_data.py
dbcpy/records/game_tip_record.py
dbcpy/records/item_display_info.py
dbcpy/records/item_record.py
dbcpy/records/record_iterator.py
dbcpy/records/record_reader.py
dbcpy/records/sound_entries.py
dbcpy/records/spell_icon.py
dbcpy/records/spell_record.py
dbcpy-1.0.9.dist-info/LICENSE
dbcpy-1.0.9.dist-info/METADATA
dbcpy-1.0.9.dist-info/WHEEL
dbcpy-1.0.9.dist-info/top_level.txt
dbcpy-1.0.9.dist-info/RECORD
