Metadata-Version: 2.1
Name: dbcpy
Version: 1.0.9
Summary: simple python library for reading WoW's DBC files
Home-page: https://github.com/jacadzaca/dbcpy
Author: jacadzaca
Author-email: vitouejj@gmail.com
License: LGPL3
License-File: LICENSE
